beacon/__init__.py
beacon/__version__.py
beacon-0.0.2.dist-info/METADATA
beacon-0.0.2.dist-info/RECORD
beacon-0.0.2.dist-info/WHEEL
beacon-0.0.2.dist-info/top_level.txt
